kagent/crewai/__init__.py
kagent/crewai/_a2a.py
kagent/crewai/_executor.py
kagent/crewai/_listeners.py
kagent/crewai/_memory.py
kagent/crewai/_state.py
kagent_crewai-0.7.8.dist-info/METADATA
kagent_crewai-0.7.8.dist-info/WHEEL
kagent_crewai-0.7.8.dist-info/RECORD
