Metadata-Version: 2.4
Name: kagent-crewai
Version: 0.7.8
Summary: CrewAI integration for KAgent with A2A server support
Requires-Python: >=3.13
Requires-Dist: a2a-sdk[http-server]>=0.3.1
Requires-Dist: crewai[tools]<1.0.0,>=0.193.2
Requires-Dist: fastapi>=0.100.0
Requires-Dist: google-genai>=1.21.1
Requires-Dist: httpx>=0.25.0
Requires-Dist: kagent-core
Requires-Dist: opentelemetry-instrumentation-crewai>=0.47.3
Requires-Dist: pydantic>=2.0.0
Requires-Dist: typing-extensions>=4.0.0
Requires-Dist: uvicorn>=0.20.0
Provides-Extra: dev
Requires-Dist: black>=23.0.0; extra == 'dev'
Requires-Dist: pytest-asyncio>=0.21.0; extra == 'dev'
Requires-Dist: pytest>=7.0.0; extra == 'dev'
Requires-Dist: ruff>=0.1.0; extra == 'dev'
